{
  "clean_text": "education means considerably more than just teaching a student to read, write, and manipulate numbers. computers, the internet, and advanced electronic devices are becoming essential in everyday life and have changed the way information is gathered. how this new technology is utilized in the curriculum and managed by teachers will have an important role to play in widening the resource and knowledge base for all students. technology affects the way teachers teach and students learn. to make the best use of information technology (it), schools need a workable plan to fully integrate it into all aspects of the curriculum so students are taught how, why, and when to use technology to further enhance their learning. if a school does not have a clear plan of how and why it wishes to implement it, then it runs the risk of wasting money. in schools today, nearly all classrooms have access to a computer. however, many schools mistake this as incorporating information technology into the curriculum. school staff need to research what it is available and what would best serve the school's purpose, not simply purchase the latest equipment. there should be a policy stating how it is going to assist pupils' development and what teachers want pupils to achieve (reksten, 2000). staff members need to be clear about what they want it to do for them before they can start incorporating it into their lessons. the only way information technology is going to be useful to schools is if all staff members are well-informed and fully supported. it is the principal's responsibility, and should be part of the school's plan, to ensure that all staff are consulted about the changes, and that the change is carefully organised. some teachers may be resistant, especially if they have not had much experience with computers, so training teachers is essential in implementing it into the school curriculum. staff members must feel involved in the process of acquiring technology, and in learning how to operate it, in order for them to increase their confidence in using it as a curriculum tool. teachers are only going to be able to incorporate it into their lessons if they are competent users themselves (reksten, 2000). in addition, teachers need to be aware that it within the classroom is extremely flexible, but that they need to plan what purpose it serves in each lesson. the skills a child learns are the important part of any lesson, and it is the same with technology. it needs to be used and understood in all subjects in the same way as the ability to read is necessary for all subjects, and “must be used across the curriculum, in the same way that a pen and pencil are used in most subject areas” (ager, 2000, p. 15). the best way to plan the use of it in the classroom is to approach it as simply a learning tool that is more advanced (and more exciting) than the traditional pen and paper. it is vitally important for students to be taught the strategies for using it. children also need to be fully informed about the capabilities of it before being asked to use it. pupils should be aware that the contexts in which they use it will change, and they need to know what the appropriate use of it is and what is not. whilst it is important that children learn to use it effectively, teachers must emphasise that it is not always suitable. according to apter (1968), the danger is that the “computer dehumanizes people and inevitably leads them to act like machines themselves” (p. 58). teachers must make sure they plan to use variety in their lessons. too much it instruction may be just as harmful to a child as not enough. the usefulness of it in the classroom, as with any learning tool, depends on the innovation and imagination of the teacher. it is imperative, though, that the implementation of it into a school is carefully planned. the current information explosion makes it essential that it be used extensively within the classroom so children know how to use it appropriately and effectively. teachers must, therefore, be fully informed about what kinds of it are available and whether or not they are appropriate for classroom use. school boards and teachers must therefore ensure that all staff have a clear plan about what they want their students to achieve through it. the appropriate incorporation of it into the classroom will broaden the minds and skills of students, allowing them to be better prepared for further technological advances.",
  "most_common_words": {
    "teachers": 11,
    "use": 10,
    "technology": 8,
    "need": 7,
    "plan": 7,
    "way": 6,
    "curriculum": 6,
    "students": 6,
    "schools": 6,
    "staff": 6
  },
  "sentences": [
    "education means considerably more than just teaching a student to read, write, and manipulate numbers.",
    "computers, the internet, and advanced electronic devices are becoming essential in everyday life and have changed the way information is gathered.",
    "how this new technology is utilized in the curriculum and managed by teachers will have an important role to play in widening the resource and knowledge base for all students.",
    "technology affects the way teachers teach and students learn.",
    "to make the best use of information technology (it), schools need a workable plan to fully integrate it into all aspects of the curriculum so students are taught how, why, and when to use technology to further enhance their learning.",
    "if a school does not have a clear plan of how and why it wishes to implement it, then it runs the risk of wasting money.",
    "in schools today, nearly all classrooms have access to a computer.",
    "however, many schools mistake this as incorporating information technology into the curriculum.",
    "school staff need to research what it is available and what would best serve the school's purpose, not simply purchase the latest equipment.",
    "there should be a policy stating how it is going to assist pupils' development and what teachers want pupils to achieve (reksten, 2000).",
    "staff members need to be clear about what they want it to do for them before they can start incorporating it into their lessons.",
    "the only way information technology is going to be useful to schools is if all staff members are well-informed and fully supported.",
    "it is the principal's responsibility, and should be part of the school's plan, to ensure that all staff are consulted about the changes, and that the change is carefully organised.",
    "some teachers may be resistant, especially if they have not had much experience with computers, so training teachers is essential in implementing it into the school curriculum.",
    "staff members must feel involved in the process of acquiring technology, and in learning how to operate it, in order for them to increase their confidence in using it as a curriculum tool.",
    "teachers are only going to be able to incorporate it into their lessons if they are competent users themselves (reksten, 2000).",
    "in addition, teachers need to be aware that it within the classroom is extremely flexible, but that they need to plan what purpose it serves in each lesson.",
    "the skills a child learns are the important part of any lesson, and it is the same with technology.",
    "it needs to be used and understood in all subjects in the same way as the ability to read is necessary for all subjects, and “must be used across the curriculum, in the same way that a pen and pencil are used in most subject areas” (ager, 2000, p. 15).",
    "the best way to plan the use of it in the classroom is to approach it as simply a learning tool that is more advanced (and more exciting) than the traditional pen and paper.",
    "it is vitally important for students to be taught the strategies for using it.",
    "children also need to be fully informed about the capabilities of it before being asked to use it.",
    "pupils should be aware that the contexts in which they use it will change, and they need to know what the appropriate use of it is and what is not.",
    "whilst it is important that children learn to use it effectively, teachers must emphasise that it is not always suitable.",
    "according to apter (1968), the danger is that the “computer dehumanizes people and inevitably leads them to act like machines themselves” (p. 58).",
    "teachers must make sure they plan to use variety in their lessons.",
    "too much it instruction may be just as harmful to a child as not enough.",
    "the usefulness of it in the classroom, as with any learning tool, depends on the innovation and imagination of the teacher.",
    "it is imperative, though, that the implementation of it into a school is carefully planned.",
    "the current information explosion makes it essential that it be used extensively within the classroom so children know how to use it appropriately and effectively.",
    "teachers must, therefore, be fully informed about what kinds of it are available and whether or not they are appropriate for classroom use.",
    "school boards and teachers must therefore ensure that all staff have a clear plan about what they want their students to achieve through it.",
    "the appropriate incorporation of it into the classroom will broaden the minds and skills of students, allowing them to be better prepared for further technological advances."
  ],
  "stems": {
    "educ": [
      "education"
    ],
    "mean": [
      "means"
    ],
    "consider": [
      "considerably"
    ],
    "teach": [
      "teaching",
      "teach"
    ],
    "student": [
      "student",
      "students",
      "students",
      "students",
      "students",
      "students",
      "students"
    ],
    "read": [
      "read",
      "read"
    ],
    "write": [
      "write"
    ],
    "manipul": [
      "manipulate"
    ],
    "number": [
      "numbers"
    ],
    "comput": [
      "computers",
      "computer",
      "computers",
      "computer"
    ],
    "internet": [
      "internet"
    ],
    "advanc": [
      "advanced",
      "advanced",
      "advances"
    ],
    "electron": [
      "electronic"
    ],
    "devic": [
      "devices"
    ],
    "becom": [
      "becoming"
    ],
    "essenti": [
      "essential",
      "essential",
      "essential"
    ],
    "everyday": [
      "everyday"
    ],
    "life": [
      "life"
    ],
    "chang": [
      "changed",
      "changes",
      "change",
      "change"
    ],
    "way": [
      "way",
      "way",
      "way",
      "way",
      "way",
      "way"
    ],
    "inform": [
      "information",
      "information",
      "information",
      "information",
      "informed",
      "information",
      "informed"
    ],
    "gather": [
      "gathered"
    ],
    "new": [
      "new"
    ],
    "technolog": [
      "technology",
      "technology",
      "technology",
      "technology",
      "technology",
      "technology",
      "technology",
      "technology",
      "technological"
    ],
    "util": [
      "utilized"
    ],
    "curriculum": [
      "curriculum",
      "curriculum",
      "curriculum",
      "curriculum",
      "curriculum",
      "curriculum"
    ],
    "manag": [
      "managed"
    ],
    "teacher": [
      "teachers",
      "teachers",
      "teachers",
      "teachers",
      "teachers",
      "teachers",
      "teachers",
      "teachers",
      "teachers",
      "teacher",
      "teachers",
      "teachers"
    ],
    "import": [
      "important",
      "important",
      "important",
      "important"
    ],
    "role": [
      "role"
    ],
    "play": [
      "play"
    ],
    "widen": [
      "widening"
    ],
    "resourc": [
      "resource"
    ],
    "knowledg": [
      "knowledge"
    ],
    "base": [
      "base"
    ],
    "affect": [
      "affects"
    ],
    "learn": [
      "learn",
      "learning",
      "learning",
      "learns",
      "learning",
      "learn",
      "learning"
    ],
    "make": [
      "make",
      "make",
      "makes"
    ],
    "best": [
      "best",
      "best",
      "best"
    ],
    "use": [
      "use",
      "use",
      "useful",
      "using",
      "used",
      "used",
      "used",
      "use",
      "using",
      "use",
      "use",
      "use",
      "use",
      "use",
      "usefulness",
      "used",
      "use",
      "use"
    ],
    "school": [
      "schools",
      "school",
      "schools",
      "schools",
      "school",
      "schools",
      "schools",
      "schools",
      "school",
      "school",
      "school"
    ],
    "need": [
      "need",
      "need",
      "need",
      "need",
      "need",
      "needs",
      "need",
      "need"
    ],
    "workabl": [
      "workable"
    ],
    "plan": [
      "plan",
      "plan",
      "plan",
      "plan",
      "plan",
      "plan",
      "planned",
      "plan"
    ],
    "fulli": [
      "fully",
      "fully",
      "fully",
      "fully"
    ],
    "integr": [
      "integrate"
    ],
    "aspect": [
      "aspects"
    ],
    "taught": [
      "taught",
      "taught"
    ],
    "enhanc": [
      "enhance"
    ],
    "clear": [
      "clear",
      "clear",
      "clear"
    ],
    "wish": [
      "wishes"
    ],
    "implement": [
      "implement",
      "implementing",
      "implementation"
    ],
    "run": [
      "runs"
    ],
    "risk": [
      "risk"
    ],
    "wast": [
      "wasting"
    ],
    "money": [
      "money"
    ],
    "today": [
      "today"
    ],
    "nearli": [
      "nearly"
    ],
    "classroom": [
      "classrooms",
      "classroom",
      "classroom",
      "classroom",
      "classroom",
      "classroom",
      "classroom"
    ],
    "access": [
      "access"
    ],
    "howev": [
      "however"
    ],
    "mani": [
      "many"
    ],
    "mistak": [
      "mistake"
    ],
    "incorpor": [
      "incorporating",
      "incorporating",
      "incorporate",
      "incorporation"
    ],
    "staff": [
      "staff",
      "staff",
      "staff",
      "staff",
      "staff",
      "staff"
    ],
    "research": [
      "research"
    ],
    "avail": [
      "available",
      "available"
    ],
    "would": [
      "would"
    ],
    "serv": [
      "serve",
      "serves"
    ],
    "purpos": [
      "purpose",
      "purpose"
    ],
    "simpli": [
      "simply",
      "simply"
    ],
    "purchas": [
      "purchase"
    ],
    "latest": [
      "latest"
    ],
    "equip": [
      "equipment"
    ],
    "polici": [
      "policy"
    ],
    "state": [
      "stating"
    ],
    "go": [
      "going",
      "going",
      "going"
    ],
    "assist": [
      "assist"
    ],
    "pupil": [
      "pupils",
      "pupils",
      "pupils"
    ],
    "develop": [
      "development"
    ],
    "want": [
      "want",
      "want",
      "want"
    ],
    "achiev": [
      "achieve",
      "achieve"
    ],
    "reksten": [
      "reksten",
      "reksten"
    ],
    "2000": [
      "2000",
      "2000",
      "2000"
    ],
    "member": [
      "members",
      "members",
      "members"
    ],
    "start": [
      "start"
    ],
    "lesson": [
      "lessons",
      "lessons",
      "lesson",
      "lesson",
      "lessons"
    ],
    "wellinform": [
      "wellinformed"
    ],
    "support": [
      "supported"
    ],
    "princip": [
      "principals"
    ],
    "respons": [
      "responsibility"
    ],
    "part": [
      "part",
      "part"
    ],
    "ensur": [
      "ensure",
      "ensure"
    ],
    "consult": [
      "consulted"
    ],
    "care": [
      "carefully",
      "carefully"
    ],
    "organis": [
      "organised"
    ],
    "may": [
      "may",
      "may"
    ],
    "resist": [
      "resistant"
    ],
    "especi": [
      "especially"
    ],
    "much": [
      "much",
      "much"
    ],
    "experi": [
      "experience"
    ],
    "train": [
      "training"
    ],
    "must": [
      "must",
      "must",
      "must",
      "must",
      "must",
      "must"
    ],
    "feel": [
      "feel"
    ],
    "involv": [
      "involved"
    ],
    "process": [
      "process"
    ],
    "acquir": [
      "acquiring"
    ],
    "oper": [
      "operate"
    ],
    "order": [
      "order"
    ],
    "increas": [
      "increase"
    ],
    "confid": [
      "confidence"
    ],
    "tool": [
      "tool",
      "tool",
      "tool"
    ],
    "abl": [
      "able"
    ],
    "compet": [
      "competent"
    ],
    "user": [
      "users"
    ],
    "addit": [
      "addition"
    ],
    "awar": [
      "aware",
      "aware"
    ],
    "within": [
      "within",
      "within"
    ],
    "extrem": [
      "extremely"
    ],
    "flexibl": [
      "flexible"
    ],
    "skill": [
      "skills",
      "skills"
    ],
    "child": [
      "child",
      "child"
    ],
    "understood": [
      "understood"
    ],
    "subject": [
      "subjects",
      "subjects",
      "subject"
    ],
    "abil": [
      "ability"
    ],
    "necessari": [
      "necessary"
    ],
    "across": [
      "across"
    ],
    "pen": [
      "pen",
      "pen"
    ],
    "pencil": [
      "pencil"
    ],
    "area": [
      "areas"
    ],
    "ager": [
      "ager"
    ],
    "p": [
      "p",
      "p"
    ],
    "15": [
      "15"
    ],
    "approach": [
      "approach"
    ],
    "excit": [
      "exciting"
    ],
    "tradit": [
      "traditional"
    ],
    "paper": [
      "paper"
    ],
    "vital": [
      "vitally"
    ],
    "strategi": [
      "strategies"
    ],
    "children": [
      "children",
      "children",
      "children"
    ],
    "also": [
      "also"
    ],
    "capabl": [
      "capabilities"
    ],
    "ask": [
      "asked"
    ],
    "context": [
      "contexts"
    ],
    "know": [
      "know",
      "know"
    ],
    "appropri": [
      "appropriate",
      "appropriately",
      "appropriate",
      "appropriate"
    ],
    "whilst": [
      "whilst"
    ],
    "effect": [
      "effectively",
      "effectively"
    ],
    "emphasis": [
      "emphasise"
    ],
    "alway": [
      "always"
    ],
    "suitabl": [
      "suitable"
    ],
    "accord": [
      "according"
    ],
    "apter": [
      "apter"
    ],
    "1968": [
      "1968"
    ],
    "danger": [
      "danger"
    ],
    "dehuman": [
      "dehumanizes"
    ],
    "peopl": [
      "people"
    ],
    "inevit": [
      "inevitably"
    ],
    "lead": [
      "leads"
    ],
    "act": [
      "act"
    ],
    "like": [
      "like"
    ],
    "machin": [
      "machines"
    ],
    "58": [
      "58"
    ],
    "sure": [
      "sure"
    ],
    "varieti": [
      "variety"
    ],
    "instruct": [
      "instruction"
    ],
    "harm": [
      "harmful"
    ],
    "enough": [
      "enough"
    ],
    "depend": [
      "depends"
    ],
    "innov": [
      "innovation"
    ],
    "imagin": [
      "imagination"
    ],
    "imper": [
      "imperative"
    ],
    "though": [
      "though"
    ],
    "current": [
      "current"
    ],
    "explos": [
      "explosion"
    ],
    "extens": [
      "extensively"
    ],
    "therefor": [
      "therefore",
      "therefore"
    ],
    "kind": [
      "kinds"
    ],
    "whether": [
      "whether"
    ],
    "board": [
      "boards"
    ],
    "broaden": [
      "broaden"
    ],
    "mind": [
      "minds"
    ],
    "allow": [
      "allowing"
    ],
    "better": [
      "better"
    ],
    "prepar": [
      "prepared"
    ]
  },
  "lemmas": {
    "education": [
      "education"
    ],
    "mean": [
      "means"
    ],
    "considerably": [
      "considerably"
    ],
    "teaching": [
      "teaching"
    ],
    "student": [
      "student",
      "students"
    ],
    "read": [
      "read"
    ],
    "write": [
      "write"
    ],
    "manipulate": [
      "manipulate"
    ],
    "number": [
      "numbers"
    ],
    "computer": [
      "computer",
      "computers"
    ],
    "internet": [
      "internet"
    ],
    "advanced": [
      "advanced"
    ],
    "electronic": [
      "electronic"
    ],
    "device": [
      "devices"
    ],
    "becoming": [
      "becoming"
    ],
    "essential": [
      "essential"
    ],
    "everyday": [
      "everyday"
    ],
    "life": [
      "life"
    ],
    "changed": [
      "changed"
    ],
    "way": [
      "way"
    ],
    "information": [
      "information"
    ],
    "gathered": [
      "gathered"
    ],
    "new": [
      "new"
    ],
    "technology": [
      "technology"
    ],
    "utilized": [
      "utilized"
    ],
    "curriculum": [
      "curriculum"
    ],
    "managed": [
      "managed"
    ],
    "teacher": [
      "teachers",
      "teacher"
    ],
    "important": [
      "important"
    ],
    "role": [
      "role"
    ],
    "play": [
      "play"
    ],
    "widening": [
      "widening"
    ],
    "resource": [
      "resource"
    ],
    "knowledge": [
      "knowledge"
    ],
    "base": [
      "base"
    ],
    "affect": [
      "affects"
    ],
    "teach": [
      "teach"
    ],
    "learn": [
      "learn"
    ],
    "make": [
      "makes",
      "make"
    ],
    "best": [
      "best"
    ],
    "use": [
      "use"
    ],
    "school": [
      "school",
      "schools"
    ],
    "need": [
      "need",
      "needs"
    ],
    "workable": [
      "workable"
    ],
    "plan": [
      "plan"
    ],
    "fully": [
      "fully"
    ],
    "integrate": [
      "integrate"
    ],
    "aspect": [
      "aspects"
    ],
    "taught": [
      "taught"
    ],
    "enhance": [
      "enhance"
    ],
    "learning": [
      "learning"
    ],
    "clear": [
      "clear"
    ],
    "wish": [
      "wishes"
    ],
    "implement": [
      "implement"
    ],
    "run": [
      "runs"
    ],
    "risk": [
      "risk"
    ],
    "wasting": [
      "wasting"
    ],
    "money": [
      "money"
    ],
    "today": [
      "today"
    ],
    "nearly": [
      "nearly"
    ],
    "classroom": [
      "classroom",
      "classrooms"
    ],
    "access": [
      "access"
    ],
    "however": [
      "however"
    ],
    "many": [
      "many"
    ],
    "mistake": [
      "mistake"
    ],
    "incorporating": [
      "incorporating"
    ],
    "staff": [
      "staff"
    ],
    "research": [
      "research"
    ],
    "available": [
      "available"
    ],
    "would": [
      "would"
    ],
    "serve": [
      "serve"
    ],
    "purpose": [
      "purpose"
    ],
    "simply": [
      "simply"
    ],
    "purchase": [
      "purchase"
    ],
    "latest": [
      "latest"
    ],
    "equipment": [
      "equipment"
    ],
    "policy": [
      "policy"
    ],
    "stating": [
      "stating"
    ],
    "going": [
      "going"
    ],
    "assist": [
      "assist"
    ],
    "pupil": [
      "pupils"
    ],
    "development": [
      "development"
    ],
    "want": [
      "want"
    ],
    "achieve": [
      "achieve"
    ],
    "reksten": [
      "reksten"
    ],
    "2000": [
      "2000"
    ],
    "member": [
      "members"
    ],
    "start": [
      "start"
    ],
    "lesson": [
      "lesson",
      "lessons"
    ],
    "useful": [
      "useful"
    ],
    "wellinformed": [
      "wellinformed"
    ],
    "supported": [
      "supported"
    ],
    "principal": [
      "principals"
    ],
    "responsibility": [
      "responsibility"
    ],
    "part": [
      "part"
    ],
    "ensure": [
      "ensure"
    ],
    "consulted": [
      "consulted"
    ],
    "change": [
      "changes",
      "change"
    ],
    "carefully": [
      "carefully"
    ],
    "organised": [
      "organised"
    ],
    "may": [
      "may"
    ],
    "resistant": [
      "resistant"
    ],
    "especially": [
      "especially"
    ],
    "much": [
      "much"
    ],
    "experience": [
      "experience"
    ],
    "training": [
      "training"
    ],
    "implementing": [
      "implementing"
    ],
    "must": [
      "must"
    ],
    "feel": [
      "feel"
    ],
    "involved": [
      "involved"
    ],
    "process": [
      "process"
    ],
    "acquiring": [
      "acquiring"
    ],
    "operate": [
      "operate"
    ],
    "order": [
      "order"
    ],
    "increase": [
      "increase"
    ],
    "confidence": [
      "confidence"
    ],
    "using": [
      "using"
    ],
    "tool": [
      "tool"
    ],
    "able": [
      "able"
    ],
    "incorporate": [
      "incorporate"
    ],
    "competent": [
      "competent"
    ],
    "user": [
      "users"
    ],
    "addition": [
      "addition"
    ],
    "aware": [
      "aware"
    ],
    "within": [
      "within"
    ],
    "extremely": [
      "extremely"
    ],
    "flexible": [
      "flexible"
    ],
    "serf": [
      "serves"
    ],
    "skill": [
      "skills"
    ],
    "child": [
      "children",
      "child"
    ],
    "learns": [
      "learns"
    ],
    "used": [
      "used"
    ],
    "understood": [
      "understood"
    ],
    "subject": [
      "subject",
      "subjects"
    ],
    "ability": [
      "ability"
    ],
    "necessary": [
      "necessary"
    ],
    "across": [
      "across"
    ],
    "pen": [
      "pen"
    ],
    "pencil": [
      "pencil"
    ],
    "area": [
      "areas"
    ],
    "ager": [
      "ager"
    ],
    "p": [
      "p"
    ],
    "15": [
      "15"
    ],
    "approach": [
      "approach"
    ],
    "exciting": [
      "exciting"
    ],
    "traditional": [
      "traditional"
    ],
    "paper": [
      "paper"
    ],
    "vitally": [
      "vitally"
    ],
    "strategy": [
      "strategies"
    ],
    "also": [
      "also"
    ],
    "informed": [
      "informed"
    ],
    "capability": [
      "capabilities"
    ],
    "asked": [
      "asked"
    ],
    "context": [
      "contexts"
    ],
    "know": [
      "know"
    ],
    "appropriate": [
      "appropriate"
    ],
    "whilst": [
      "whilst"
    ],
    "effectively": [
      "effectively"
    ],
    "emphasise": [
      "emphasise"
    ],
    "always": [
      "always"
    ],
    "suitable": [
      "suitable"
    ],
    "according": [
      "according"
    ],
    "apter": [
      "apter"
    ],
    "1968": [
      "1968"
    ],
    "danger": [
      "danger"
    ],
    "dehumanizes": [
      "dehumanizes"
    ],
    "people": [
      "people"
    ],
    "inevitably": [
      "inevitably"
    ],
    "lead": [
      "leads"
    ],
    "act": [
      "act"
    ],
    "like": [
      "like"
    ],
    "machine": [
      "machines"
    ],
    "58": [
      "58"
    ],
    "sure": [
      "sure"
    ],
    "variety": [
      "variety"
    ],
    "instruction": [
      "instruction"
    ],
    "harmful": [
      "harmful"
    ],
    "enough": [
      "enough"
    ],
    "usefulness": [
      "usefulness"
    ],
    "depends": [
      "depends"
    ],
    "innovation": [
      "innovation"
    ],
    "imagination": [
      "imagination"
    ],
    "imperative": [
      "imperative"
    ],
    "though": [
      "though"
    ],
    "implementation": [
      "implementation"
    ],
    "planned": [
      "planned"
    ],
    "current": [
      "current"
    ],
    "explosion": [
      "explosion"
    ],
    "extensively": [
      "extensively"
    ],
    "appropriately": [
      "appropriately"
    ],
    "therefore": [
      "therefore"
    ],
    "kind": [
      "kinds"
    ],
    "whether": [
      "whether"
    ],
    "board": [
      "boards"
    ],
    "incorporation": [
      "incorporation"
    ],
    "broaden": [
      "broaden"
    ],
    "mind": [
      "minds"
    ],
    "allowing": [
      "allowing"
    ],
    "better": [
      "better"
    ],
    "prepared": [
      "prepared"
    ],
    "technological": [
      "technological"
    ],
    "advance": [
      "advances"
    ]
  }
}